{
  "trade_date": "20260310",
  "data_source": "Tushare Pro (真实数据)",
  "market_strength": 0.36,
  "total_stocks": 19,
  "total_sectors": 13,
  "sectors": [
    {
      "sector_name": "元器件",
      "new_high_count": 3,
      "stock_count": 3,
      "avg_consecutive_days": 1.0,
      "stocks": [
        {
          "code": "002384",
          "name": "东山精密",
          "close": 108.06,
          "price": 108.06,
          "high_250": 108.06,
          "high_250d": 108.06,
          "consecutive_new_high_days": 1,
          "consecutive_days": 1,
          "change_pct": 10.0,
          "change": 10.0,
          "break_through": 0.0,
          "break_pct": 0.0,
          "circ_mv": 1498.06,
          "amount": 9599.79,
          "turnover": 9599.79,
          "institution_score": 10.0,
          "sector": "元器件",
          "industry": "元器件"
        },
        {
          "code": "300936",
          "name": "中英科技",
          "close": 58.54,
          "price": 58.54,
          "high_250": 58.54,
          "high_250d": 58.54,
          "consecutive_new_high_days": 1,
          "consecutive_days": 1,
          "change_pct": 20.01,
          "change": 20.01,
          "break_through": 0.0,
          "break_pct": 0.0,
          "circ_mv": 27.78,
          "amount": 484.64,
          "turnover": 484.64,
          "institution_score": 1.98,
          "sector": "元器件",
          "industry": "元器件"
        },
        {
          "code": "688655",
          "name": "迅捷兴",
          "close": 29.4,
          "price": 29.4,
          "high_250": 29.4,
          "high_250d": 29.4,
          "consecutive_new_high_days": 1,
          "consecutive_days": 1,
          "change_pct": 20.0,
          "change": 20.0,
          "break_through": 0.0,
          "break_pct": 0.0,
          "circ_mv": 39.22,
          "amount": 327.81,
          "turnover": 327.81,
          "institution_score": 1.51,
          "sector": "元器件",
          "industry": "元器件"
        }
      ]
    },
    {
      "sector_name": "新型电力",
      "new_high_count": 2,
      "stock_count": 2,
      "avg_consecutive_days": 1.0,
      "stocks": [
        {
          "code": "000537",
          "name": "绿发电力",
          "close": 10.34,
          "price": 10.34,
          "high_250": 10.34,
          "high_250d": 10.34,
          "consecutive_new_high_days": 1,
          "consecutive_days": 1,
          "change_pct": 10.0,
          "change": 10.0,
          "break_through": 0.0,
          "break_pct": 0.0,
          "circ_mv": 213.69,
          "amount": 291.64,
          "turnover": 291.64,
          "institution_score": 2.82,
          "sector": "新型电力",
          "industry": "新型电力"
        },
        {
          "code": "601778",
          "name": "晶科科技",
          "close": 5.61,
          "price": 5.61,
          "high_250": 5.61,
          "high_250d": 5.61,
          "consecutive_new_high_days": 1,
          "consecutive_days": 1,
          "change_pct": 10.0,
          "change": 10.0,
          "break_through": 0.0,
          "break_pct": 0.0,
          "circ_mv": 200.33,
          "amount": 2825.09,
          "turnover": 2825.09,
          "institution_score": 6.65,
          "sector": "新型电力",
          "industry": "新型电力"
        }
      ]
    },
    {
      "sector_name": "通信设备",
      "new_high_count": 2,
      "stock_count": 2,
      "avg_consecutive_days": 1.0,
      "stocks": [
        {
          "code": "002281",
          "name": "光迅科技",
          "close": 86.16,
          "price": 86.16,
          "high_250": 86.16,
          "high_250d": 86.16,
          "consecutive_new_high_days": 1,
          "consecutive_days": 1,
          "change_pct": 10.0,
          "change": 10.0,
          "break_through": 0.0,
          "break_pct": 0.0,
          "circ_mv": 671.6,
          "amount": 4557.44,
          "turnover": 4557.44,
          "institution_score": 10.0,
          "sector": "通信设备",
          "industry": "通信设备"
        },
        {
          "code": "603421",
          "name": "鼎信通讯",
          "close": 9.21,
          "price": 9.21,
          "high_250": 9.21,
          "high_250d": 9.21,
          "consecutive_new_high_days": 1,
          "consecutive_days": 1,
          "change_pct": 10.04,
          "change": 10.04,
          "break_through": 0.0,
          "break_pct": 0.0,
          "circ_mv": 60.07,
          "amount": 207.41,
          "turnover": 207.41,
          "institution_score": 1.25,
          "sector": "通信设备",
          "industry": "通信设备"
        }
      ]
    },
    {
      "sector_name": "建筑工程",
      "new_high_count": 2,
      "stock_count": 2,
      "avg_consecutive_days": 1.0,
      "stocks": [
        {
          "code": "601789",
          "name": "宁波建工",
          "close": 6.64,
          "price": 6.64,
          "high_250": 6.64,
          "high_250d": 6.64,
          "consecutive_new_high_days": 1,
          "consecutive_days": 1,
          "change_pct": 9.93,
          "change": 9.93,
          "break_through": 0.0,
          "break_pct": 0.0,
          "circ_mv": 72.16,
          "amount": 156.68,
          "turnover": 156.68,
          "institution_score": 1.16,
          "sector": "建筑工程",
          "industry": "建筑工程"
        },
        {
          "code": "001267",
          "name": "汇绿生态",
          "close": 45.68,
          "price": 45.68,
          "high_250": 45.68,
          "high_250d": 45.68,
          "consecutive_new_high_days": 1,
          "consecutive_days": 1,
          "change_pct": 9.99,
          "change": 9.99,
          "break_through": 0.0,
          "break_pct": 0.0,
          "circ_mv": 276.89,
          "amount": 2019.82,
          "turnover": 2019.82,
          "institution_score": 7.29,
          "sector": "建筑工程",
          "industry": "建筑工程"
        }
      ]
    },
    {
      "sector_name": "机械基件",
      "new_high_count": 2,
      "stock_count": 2,
      "avg_consecutive_days": 1.0,
      "stocks": [
        {
          "code": "300257",
          "name": "开山股份",
          "close": 34.33,
          "price": 34.33,
          "high_250": 34.33,
          "high_250d": 34.33,
          "consecutive_new_high_days": 1,
          "consecutive_days": 1,
          "change_pct": 19.99,
          "change": 19.99,
          "break_through": 0.0,
          "break_pct": 0.0,
          "circ_mv": 327.75,
          "amount": 1330.55,
          "turnover": 1330.55,
          "institution_score": 7.52,
          "sector": "机械基件",
          "industry": "机械基件"
        },
        {
          "code": "603269",
          "name": "海鸥股份",
          "close": 17.93,
          "price": 17.93,
          "high_250": 17.93,
          "high_250d": 17.93,
          "consecutive_new_high_days": 1,
          "consecutive_days": 1,
          "change_pct": 10.0,
          "change": 10.0,
          "break_through": 0.0,
          "break_pct": 0.0,
          "circ_mv": 55.36,
          "amount": 668.31,
          "turnover": 668.31,
          "institution_score": 2.88,
          "sector": "机械基件",
          "industry": "机械基件"
        }
      ]
    },
    {
      "sector_name": "种植业",
      "new_high_count": 1,
      "stock_count": 1,
      "avg_consecutive_days": 1.0,
      "stocks": [
        {
          "code": "600108",
          "name": "亚盛集团",
          "close": 5.97,
          "price": 5.97,
          "high_250": 5.97,
          "high_250d": 5.97,
          "consecutive_new_high_days": 1,
          "consecutive_days": 1,
          "change_pct": 9.94,
          "change": 9.94,
          "break_through": 0.0,
          "break_pct": 0.0,
          "circ_mv": 116.23,
          "amount": 2570.79,
          "turnover": 2570.79,
          "institution_score": 5.96,
          "sector": "种植业",
          "industry": "种植业"
        }
      ]
    },
    {
      "sector_name": "火力发电",
      "new_high_count": 1,
      "stock_count": 1,
      "avg_consecutive_days": 1.0,
      "stocks": [
        {
          "code": "600726",
          "name": "华电能源",
          "close": 3.21,
          "price": 3.21,
          "high_250": 3.21,
          "high_250d": 3.21,
          "consecutive_new_high_days": 1,
          "consecutive_days": 1,
          "change_pct": 9.93,
          "change": 9.93,
          "break_through": 0.0,
          "break_pct": 0.0,
          "circ_mv": 239.96,
          "amount": 504.53,
          "turnover": 504.53,
          "institution_score": 3.81,
          "sector": "火力发电",
          "industry": "火力发电"
        }
      ]
    },
    {
      "sector_name": "电气设备",
      "new_high_count": 1,
      "stock_count": 1,
      "avg_consecutive_days": 1.0,
      "stocks": [
        {
          "code": "002350",
          "name": "北京科锐",
          "close": 15.22,
          "price": 15.22,
          "high_250": 15.22,
          "high_250d": 15.22,
          "consecutive_new_high_days": 1,
          "consecutive_days": 1,
          "change_pct": 9.97,
          "change": 9.97,
          "break_through": 0.0,
          "break_pct": 0.0,
          "circ_mv": 80.75,
          "amount": 1002.74,
          "turnover": 1002.74,
          "institution_score": 4.3,
          "sector": "电气设备",
          "industry": "电气设备"
        }
      ]
    },
    {
      "sector_name": "机床制造",
      "new_high_count": 1,
      "stock_count": 1,
      "avg_consecutive_days": 1.0,
      "stocks": [
        {
          "code": "002903",
          "name": "宇环数控",
          "close": 30.37,
          "price": 30.37,
          "high_250": 30.37,
          "high_250d": 30.37,
          "consecutive_new_high_days": 1,
          "consecutive_days": 1,
          "change_pct": 10.0,
          "change": 10.0,
          "break_through": 0.0,
          "break_pct": 0.0,
          "circ_mv": 32.39,
          "amount": 540.7,
          "turnover": 540.7,
          "institution_score": 2.22,
          "sector": "机床制造",
          "industry": "机床制造"
        }
      ]
    },
    {
      "sector_name": "铝",
      "new_high_count": 1,
      "stock_count": 1,
      "avg_consecutive_days": 1.0,
      "stocks": [
        {
          "code": "603115",
          "name": "海星股份",
          "close": 32.0,
          "price": 32.0,
          "high_250": 32.0,
          "high_250d": 32.0,
          "consecutive_new_high_days": 1,
          "consecutive_days": 1,
          "change_pct": 10.0,
          "change": 10.0,
          "break_through": 0.0,
          "break_pct": 0.0,
          "circ_mv": 77.4,
          "amount": 277.15,
          "turnover": 277.15,
          "institution_score": 1.64,
          "sector": "铝",
          "industry": "铝"
        }
      ]
    },
    {
      "sector_name": "矿物制品",
      "new_high_count": 1,
      "stock_count": 1,
      "avg_consecutive_days": 1.0,
      "stocks": [
        {
          "code": "688300",
          "name": "联瑞新材",
          "close": 99.96,
          "price": 99.96,
          "high_250": 99.96,
          "high_250d": 99.96,
          "consecutive_new_high_days": 1,
          "consecutive_days": 1,
          "change_pct": 20.0,
          "change": 20.0,
          "break_through": 0.0,
          "break_pct": 0.0,
          "circ_mv": 241.37,
          "amount": 1813.26,
          "turnover": 1813.26,
          "institution_score": 6.99,
          "sector": "矿物制品",
          "industry": "矿物制品"
        }
      ]
    },
    {
      "sector_name": "半导体",
      "new_high_count": 1,
      "stock_count": 1,
      "avg_consecutive_days": 1.0,
      "stocks": [
        {
          "code": "688048",
          "name": "长光华芯",
          "close": 188.4,
          "price": 188.4,
          "high_250": 188.4,
          "high_250d": 188.4,
          "consecutive_new_high_days": 1,
          "consecutive_days": 1,
          "change_pct": 20.0,
          "change": 20.0,
          "break_through": 0.0,
          "break_pct": 0.0,
          "circ_mv": 332.11,
          "amount": 3317.29,
          "turnover": 3317.29,
          "institution_score": 7.74,
          "sector": "半导体",
          "industry": "半导体"
        }
      ]
    },
    {
      "sector_name": "专用机械",
      "new_high_count": 1,
      "stock_count": 1,
      "avg_consecutive_days": 1.0,
      "stocks": [
        {
          "code": "001400",
          "name": "江顺科技",
          "close": 146.04,
          "price": 146.04,
          "high_250": 146.04,
          "high_250d": 146.04,
          "consecutive_new_high_days": 1,
          "consecutive_days": 1,
          "change_pct": 10.0,
          "change": 10.0,
          "break_through": 0.0,
          "break_pct": 0.0,
          "circ_mv": 21.91,
          "amount": 304.15,
          "turnover": 304.15,
          "institution_score": 1.28,
          "sector": "专用机械",
          "industry": "专用机械"
        }
      ]
    }
  ]
}